pretix_mpesamz/__init__.py
pretix_mpesamz/apps.py
pretix_mpesamz/mpesa_api.py
pretix_mpesamz/payment.py
pretix_mpesamz/signals.py
pretix_mpesamz/locale/de/LC_MESSAGES/django.mo
pretix_mpesamz/locale/de/LC_MESSAGES/django.po
pretix_mpesamz/locale/de_Informal/.gitkeep
pretix_mpesamz/locale/de_Informal/LC_MESSAGES/django.mo
pretix_mpesamz/locale/de_Informal/LC_MESSAGES/django.po
pretix_mpesamz/static/pretix_mpesamz/.gitkeep
pretix_mpesamz/static/pretix_mpesamz/countdown.js
pretix_mpesamz/templates/pretix_mpesamz/.gitkeep
pretix_mpesamz/templates/pretix_mpesamz/checkout_payment_confirm.html
pretix_mpesamz/templates/pretix_mpesamz/checkout_payment_form.html
pretix_mpesamz/templates/pretix_mpesamz/control.html
pretix_mpesamz/templates/pretix_mpesamz/order.html
pretix_mpesamz/templates/pretix_mpesamz/payment_failed.html
pretix_mpesamz/templates/pretix_mpesamz/payment_pending.html
pretix_mpesamz/templates/pretix_mpesamz/payment_successful.html
pretix_mpesamz/templates/pretix_mpesamz/redirect.html
pretix_mpesamz/templates/pretix_mpesamz/refund_control.html
pretix_mpesa_mz-1.4.2.dist-info/LICENSE
pretix_mpesa_mz-1.4.2.dist-info/METADATA
pretix_mpesa_mz-1.4.2.dist-info/WHEEL
pretix_mpesa_mz-1.4.2.dist-info/entry_points.txt
pretix_mpesa_mz-1.4.2.dist-info/top_level.txt
pretix_mpesa_mz-1.4.2.dist-info/RECORD
