Metadata-Version: 2.1
Name: pretix-mpesa-mz
Version: 1.4.2
Summary: A plugin to allow payments through the M-Pesa mobile payment platform
Home-page: https://github.com/ivanruby/pretix-mpesa-mz
Author: Ivan Ruby
Author-email: ivanrubyds@gmail.com
License: Apache
License-File: LICENSE
